Workbook

Sheet Start Here
A1: Module 13 - Auditing & Validation | J1: YOUR JOURNEY
A2: Turn your analysis skills into CHECKS - Self-paced (capstone) | J2: 1 | K2: 2 | L2: 3 | M2: 4 | N2: 5 | O2: 6 | P2: 7 | Q2: 8 | R2: 9 | S2: 10 | T2: 11 | U2: 12 | V2: 13
A4: This is where it all comes together. Auditing means checking that data is RIGHT - does what was paid match what SHOULD have been paid? You'll reconcile each member's fee against the price list, find the one that doesn't add up, and run a few validation checks. These are the exact 'cross-check and audit' skills Scenario 2 of the assessment asks for.
A6: The core idea: expected vs actual
B7: The club has a price list: Junior 20, Senior 28, Adult 35, Family 55. Every member SHOULD pay the fee for their type. An audit compares EXPECTED (from the price list) with ACTUAL (what they paid) and flags any difference.
A9: If actual and expected don't reconcile, something needs investigating - an error, an overpayment, or a missing record.
A11: What you'll do
A12: • Look up each member's expected fee from the price list.
A13: • Reconcile the totals: actual paid vs expected, and explain the gap.
A14: • Find the mismatching member, and run validation checks (missing payments, out-of-range values).
A16: Before you start
B17: Auditing is detective work, and it's satisfying - the numbers either reconcile or they point you to a problem. There's no pressure: a wrong formula just gets fixed. Breathe (in 4, hold 4, out 6) and follow the trail.
A21: Your confidence baseline (1 = not yet, 5 = confident)
B22: Statement | G22: Rating (1-5)
B23: I can look up an expected value from a reference table
B24: I can reconcile an actual total against an expected total
B25: I can find and flag records that don't match
B26: I can run validation checks (blanks, out-of-range)

Sheet Fees
A1: Price list (Fees)
A2: The expected fee for each membership type
A4: MembershipType | B4: Fee
A5: Adult | B5: 35
A6: Family | B6: 55
A7: Junior | B7: 20
A8: Senior | B8: 28
A11: This is your reference table. VLOOKUP uses it to fetch the expected fee for any type. (Type in A5:A8, Fee in B5:B8.)

Sheet Audit
A1: Audit data: members who paid
A2: Actual=C5:C24, Expected=D5:D24 (live VLOOKUPs into the Fees price list - click one to see). Column E is yours to flag.
A4: MemberID | B4: MembershipType | C4: Actual | D4: Expected | E4: Flag (yours)
A5: 1001 | B5: Adult | C5: 35 | D5: =VLOOKUP(B5,Fees!$A$5:$B$8,2,FALSE()) -> 35
A6: 1002 | B6: Family | C6: 55 | D6: =VLOOKUP(B6,Fees!$A$5:$B$8,2,FALSE()) -> 55
A7: 1003 | B7: Junior | C7: 20 | D7: =VLOOKUP(B7,Fees!$A$5:$B$8,2,FALSE()) -> 20
A8: 1004 | B8: Senior | C8: 28 | D8: =VLOOKUP(B8,Fees!$A$5:$B$8,2,FALSE()) -> 28
A9: 1005 | B9: Adult | C9: 35 | D9: =VLOOKUP(B9,Fees!$A$5:$B$8,2,FALSE()) -> 35
A10: 1006 | B10: Adult | C10: 35 | D10: =VLOOKUP(B10,Fees!$A$5:$B$8,2,FALSE()) -> 35
A11: 1007 | B11: Family | C11: 55 | D11: =VLOOKUP(B11,Fees!$A$5:$B$8,2,FALSE()) -> 55
A12: 1008 | B12: Junior | C12: 20 | D12: =VLOOKUP(B12,Fees!$A$5:$B$8,2,FALSE()) -> 20
A13: 1009 | B13: Adult | C13: 35 | D13: =VLOOKUP(B13,Fees!$A$5:$B$8,2,FALSE()) -> 35
A14: 1010 | B14: Senior | C14: 28 | D14: =VLOOKUP(B14,Fees!$A$5:$B$8,2,FALSE()) -> 28
A15: 1011 | B15: Adult | C15: 35 | D15: =VLOOKUP(B15,Fees!$A$5:$B$8,2,FALSE()) -> 35
A16: 1012 | B16: Family | C16: 55 | D16: =VLOOKUP(B16,Fees!$A$5:$B$8,2,FALSE()) -> 55
... A24: 1020 | B24: Adult | C24: 35 | D24: =VLOOKUP(B24,Fees!$A$5:$B$8,2,FALSE()) -> 35

Sheet Club Data
A1: Data: Club Data (all members)
A2: All 23 members - Amount in column G (3 are blank: no payment)
A4: MemberID | B4: Name | C4: MembershipType | D4: JoinYear | E4: MemberSegment | F4: Tenure | G4: Amount | H4: Method | I4: AmountReview
A5: 1001 | B5: Aisha Khan | C5: Adult | D5: 2021 | E5: Full | F5: Established | G5: 35 | H5: Direct Debit | I5: Standard
A6: 1002 | B6: Tom Reilly | C6: Family | D6: 2020 | E6: Household | F6: Established | G6: 55 | H6: Direct Debit | I6: High
A7: 1003 | B7: Grace O'Neil | C7: Junior | D7: 2022 | E7: Concession | F7: Recent | G7: 20 | H7: Card | I7: Low
A8: 1004 | B8: David Patel | C8: Senior | D8: 2019 | E8: Concession | F8: Veteran | G8: 28 | H8: Card | I8: Low
A9: 1005 | B9: Maria Santos | C9: Adult | D9: 2023 | E9: Full | F9: Recent | G9: 35 | H9: Direct Debit | I9: Standard
A10: 1006 | B10: Liam Walsh | C10: Adult | D10: 2021 | E10: Full | F10: Established | G10: 35 | H10: Cash | I10: Standard
A11: 1007 | B11: Chloe Bennett | C11: Family | D11: 2022 | E11: Household | F11: Recent | G11: 55 | H11: Direct Debit | I11: High
A12: 1008 | B12: Noah Fischer | C12: Junior | D12: 2020 | E12: Concession | F12: Established | G12: 20 | H12: Card | I12: Low
A13: 1009 | B13: Priya Sharma | C13: Adult | D13: 2023 | E13: Full | F13: Recent | G13: 35 | H13: Direct Debit | I13: Standard
A14: 1010 | B14: James Murray | C14: Senior | D14: 2018 | E14: Concession | F14: Veteran | G14: 28 | H14: Card | I14: Low
A15: 1011 | B15: Sofia Rossi | C15: Adult | D15: 2022 | E15: Full | F15: Recent | G15: 35 | H15: Direct Debit | I15: Standard
A16: 1012 | B16: Ben Carter | C16: Family | D16: 2021 | E16: Household | F16: Established | G16: 55 | H16: Cash | I16: High
... A24: 1020 | B24: Lucas Meyer | C24: Adult | D24: 2020 | E24: Full | F24: Established | G24: 35 | H24: Cash | I24: Standard
A25: 1021 | B25: Freya Scott | C25: Adult | D25: 2023 | E25: Full | F25: Recent
A26: 1022 | B26: Adam Foster | C26: Senior | D26: 2021 | E26: Concession | F26: Established
A27: 1023 | B27: Isla Murphy | C27: Adult | D27: 2022 | E27: Full | F27: Recent

Sheet Task 1 - Expected Fee
A1: Task 1 - Look up the expected fee
A2: Use the price list with VLOOKUP
A4: VLOOKUP fetches the fee for a type from the Fees price list (Type in Fees!A5:A8, Fee in Fees!B5:B8). The '4th argument' FALSE means an exact match.
B6: What to work out | D6: Type this kind of formula | F6: Your result | G6: Check | J6: 🧭 Explore further
B7: Expected fee for an Adult member | D7: e.g. =VLOOKUP("Adult",Fees!A5:B8,2,FALSE) | G7: =IF(F7="","",IFERROR(IF(ABS(F7-(35))<0.01,"✓ Correct","✗ Try again"),"✗ Try again")) | J7: Explore: if your Excel has it, try =XLOOKUP("Adult",Fees!A5:A8,Fees!B5:B8) — no column number to count, and it can return a friendly 'Not found' message instead of an error. Click a cell in Audit column D to see the live VLOOKUP.
B8: Expected fee for a Family member | D8: e.g. =VLOOKUP("Family",Fees!A5:B8,2,FALSE) | G8: =IF(F8="","",IFERROR(IF(ABS(F8-(55))<0.01,"✓ Correct","✗ Try again"),"✗ Try again"))
B9: Expected fee for a Senior member | D9: e.g. =VLOOKUP("Senior",Fees!A5:B8,2,FALSE) | G9: =IF(F9="","",IFERROR(IF(ABS(F9-(28))<0.01,"✓ Correct","✗ Try again"),"✗ Try again"))
A11: 💡 On the Audit tab the Expected column is already filled this way for every paying member - VLOOKUP looked up each one's fee. Now you'll use it.

Sheet Task 2 - Reconcile
A1: Task 2 - Reconcile the totals
A2: Does what was paid match what was expected?
A4: On the Audit tab: Actual is C5:C24, Expected is D5:D24. Total them both and find the gap.
B6: What to work out | D6: Type this kind of formula | F6: Your result | G6: Check | J6: 🧭 Explore further
B7: Total ACTUALLY paid | D7: e.g. =SUM(Audit!C5:C24) | G7: =IF(F7="","",IFERROR(IF(ABS(F7-(1014))<0.01,"✓ Correct","✗ Try again"),"✗ Try again")) | J7: Explore: one-cell health check: =IF(SUM(Audit!C5:C24)=SUM(Audit!D5:D24),"Reconciled","Investigate"). Green light or red flag, nothing in between.
B8: Total EXPECTED (sum of the fees they should pay) | D8: e.g. =SUM(Audit!D5:D24) | G8: =IF(F8="","",IFERROR(IF(ABS(F8-(699))<0.01,"✓ Correct","✗ Try again"),"✗ Try again"))
B9: The gap (actual minus expected) | D9: e.g. =SUM(Audit!C5:C24)-SUM(Audit!D5:D24) | G9: =IF(F9="","",IFERROR(IF(ABS(F9-(315))<0.01,"✓ Correct","✗ Try again"),"✗ Try again"))
A11: 💡 A gap of 315 means the books don't balance against the price list. The next task finds exactly where it came from.

Sheet Task 3 - Find the Mismatch
A1: Task 3 - Find the mismatch
A2: Which member doesn't add up?
A4: Compare each member's Actual against their Expected. A flag formula labels each row; a count tells you how many are wrong. Actual=C5:C24, Expected=D5:D24.
B6: What to work out | D6: Type this kind of formula | F6: Your result | G6: Check | J6: 🧭 Explore further
B7: Flag row 19: 'CHECK' if Actual <> Expected, else 'OK' | D7: e.g. =IF(Audit!C19<>Audit!D19,"CHECK","OK") | G7: =IF(F7="","",IF(ISNUMBER(SEARCH("CHECK",F7)),"✓ Correct","✗ Try again")) | J7: Explore: automate the eyeball — select C5:D24, Home > Conditional Formatting > New Rule > formula =$C5<>$D5, red fill. The mismatch lights up by itself.
B8: How many members paid an amount different from their expected fee | D8: e.g. =SUMPRODUCT(--(Audit!C5:C24<>Audit!D5:D24)) | G8: =IF(F8="","",IFERROR(IF(ABS(F8-(1))<0.01,"✓ Correct","✗ Try again"),"✗ Try again"))
B9: Which MemberID is the mismatch? (fill column E with the flag, then read its MemberID) | D9: e.g. 1015 | G9: =IF(F9="","",IFERROR(IF(ABS(F9-(1015))<0.01,"✓ Correct","✗ Try again"),"✗ Try again"))
B11: Case closed: exactly 1 member (1015) paid 350 instead of the expected 35 for an Adult - an overpayment of 315, which is the WHOLE gap you found in Task 2. That is a complete audit: you found the discrepancy, quantified it, and explained the total. You'd flag member 1015 for someone to investigate (a typo? a one-off? a refund due?).

Sheet Task 4 - Validation Checks
A1: Task 4 - Other validation checks
A2: Quick checks every data set should pass
A4: Beyond the fee reconciliation, run a couple of standard validations on the full membership (Club Data, Amount in G5:G27).
B6: What to work out | D6: Type this kind of formula | F6: Your result | G6: Check | J6: 🧭 Explore further
B7: How many members have NO payment recorded (blank Amount) | D7: e.g. =COUNTBLANK('Club Data'!G5:G27) | G7: =IF(F7="","",IFERROR(IF(ABS(F7-(3))<0.01,"✓ Correct","✗ Try again"),"✗ Try again")) | J7: Explore: try the opposite range check too: =COUNTIF(range,"<20") — payments below the cheapest fee. And =COUNTIF(range,"<0") should ALWAYS be zero; if not, stop everything.
B8: How many payments are above the top fee of 55 (out of expected range) | D8: e.g. =COUNTIF('Club Data'!G5:G27,">55") | G8: =IF(F8="","",IFERROR(IF(ABS(F8-(1))<0.01,"✓ Correct","✗ Try again"),"✗ Try again"))
A10: 💡 Findings: 3 members have no payment on file (chase or write off?), and 1 payment is above any valid fee (the 350 again). Each is a flag for follow-up - validation is about RAISING questions, not silently fixing.

Sheet Support
A1: Support - auditing toolkit
A2: Type = first, then the function.
B4: VLOOKUP | C4: VLOOKUP(value, table, column_number, FALSE) - fetches a matching value from a reference table. FALSE = exact match. Example: VLOOKUP("Adult",Fees!A5:B8,2,FALSE).
B5: Reconcile totals | C5: SUM the actual column and SUM the expected column; subtract. A non-zero gap means something to investigate.
B6: Flag a mismatch (IF + <>) | C6: IF(actual<>expected,"CHECK","OK"). The <> means 'not equal to'. Copy it down the column.
B7: Count mismatches | C7: SUMPRODUCT(--(rangeA<>rangeB)) counts how many rows differ. (The -- turns TRUE/FALSE into 1/0.)
B8: Count blanks (missing data) | C8: COUNTBLANK(range) - how many cells are empty. Missing records are a classic data-quality issue.
B9: Out-of-range check | C9: COUNTIF(range,">55") or "<0" - counts values outside what's valid. Flag, don't delete.
B10: Document findings | C10: An audit ends with a note: what you checked, what you found, and what needs follow-up. That record IS the deliverable.

Sheet Stretch
A1: Stretch - the auditor's mindset
A2: Judgement, not just formulas
A4: A good auditor explains findings and proposes action - they don't just spot numbers.
A6: Write the audit note (no marking)
B7: Write 2-3 sentences you would hand to the club manager about member 1015: what you found, by how much, and what they should do.
B8: You found 3 members with no payment. List three DIFFERENT innocent explanations - and three that would worry you.
B9: Reconciliation caught an OVERpayment. What check would catch the opposite - members who paid too LITTLE or not at all?
B10: Why is 'flag for investigation' usually safer than 'correct it yourself' when you find an anomaly?

Sheet Confidence & Next Steps
A1: Confidence & Next Steps | J1: YOUR JOURNEY
A2: You've completed the analysis block | J2: 1 | K2: 2 | L2: 3 | M2: 4 | N2: 5 | O2: 6 | P2: 7 | Q2: 8 | R2: 9 | S2: 10 | T2: 11 | U2: 12 | V2: 13
A4: Mastery gate - tick all of these to finish the block
A5: Type x in each yellow box you can tick.
D6: I can look up an expected value with VLOOKUP
D7: I reconciled the actual total against the expected total
D8: I flagged the mismatch and identified the member
D9: I ran validation checks for blanks and out-of-range values
D10: I can write up findings and recommend follow-up (not silently fix)
A12: Re-rate your confidence (compare with your baseline)
A13: Seeing these rise from your Module 13 baseline is the goal.
B14: Statement | E14: Now (1-5)
B15: I can look up an expected value from a reference table
B16: I can reconcile an actual total against an expected total
B17: I can find and flag records that don't match
B18: I can run validation checks (blanks, out-of-range)
B20: Well done - that completes the analysis & validation block (Modules 7-13): basics, IF, IFS, forecasting & regression, pivots, dashboards, and auditing - all on one continuous dataset, and all mapping to Scenario 2 of the assessment. Together with Modules 1-6 (import, clean, shape, blend, patterns) you now have the full data-handling journey a Data Technician needs for the scenario demonstration.
